streamlit_tree_select/__init__.py
streamlit_tree_select/frontend/build/.DS_Store
streamlit_tree_select/frontend/build/asset-manifest.json
streamlit_tree_select/frontend/build/bootstrap.min.css
streamlit_tree_select/frontend/build/index.html
streamlit_tree_select/frontend/build/precache-manifest.56f8a850ffff7e23f3856a86a6a232db.js
streamlit_tree_select/frontend/build/precache-manifest.8d300b96e6193fdeb27135eacb72a2ef.js
streamlit_tree_select/frontend/build/precache-manifest.a01866bcb7834355e611501d7bd96ac8.js
streamlit_tree_select/frontend/build/react-checkbox-tree.css
streamlit_tree_select/frontend/build/service-worker.js
streamlit_tree_select/frontend/build/font-awesome/.DS_Store
streamlit_tree_select/frontend/build/font-awesome/css/font-awesome.css
streamlit_tree_select/frontend/build/font-awesome/css/font-awesome.min.css
streamlit_tree_select/frontend/build/font-awesome/fonts/FontAwesome.otf
streamlit_tree_select/frontend/build/font-awesome/fonts/fontawesome-webfont.eot
streamlit_tree_select/frontend/build/font-awesome/fonts/fontawesome-webfont.svg
streamlit_tree_select/frontend/build/font-awesome/fonts/fontawesome-webfont.ttf
streamlit_tree_select/frontend/build/font-awesome/fonts/fontawesome-webfont.woff
streamlit_tree_select/frontend/build/font-awesome/fonts/fontawesome-webfont.woff2
streamlit_tree_select/frontend/build/font-awesome/less/animated.less
streamlit_tree_select/frontend/build/font-awesome/less/bordered-pulled.less
streamlit_tree_select/frontend/build/font-awesome/less/core.less
streamlit_tree_select/frontend/build/font-awesome/less/fixed-width.less
streamlit_tree_select/frontend/build/font-awesome/less/font-awesome.less
streamlit_tree_select/frontend/build/font-awesome/less/icons.less
streamlit_tree_select/frontend/build/font-awesome/less/larger.less
streamlit_tree_select/frontend/build/font-awesome/less/list.less
streamlit_tree_select/frontend/build/font-awesome/less/mixins.less
streamlit_tree_select/frontend/build/font-awesome/less/path.less
streamlit_tree_select-0.0.4.dist-info/LICENSE
streamlit_tree_select-0.0.4.dist-info/METADATA
streamlit_tree_select-0.0.4.dist-info/WHEEL
streamlit_tree_select-0.0.4.dist-info/top_level.txt
streamlit_tree_select-0.0.4.dist-info/RECORD
