Metadata-Version: 2.1
Name: streamlit-tree-select
Version: 0.0.4
Summary: A simple and elegant checkbox tree for Streamlit.
Home-page: https://github.com/Schluca/streamlit_tree_select
Author: Schluca
Author-email: 
Requires-Python: >=3.6
License-File: LICENSE
Requires-Dist: streamlit (>=0.63)
